context_printer/__init__.py
context_printer/context_printer.py
contextprinter/__init__.py
contextprinter/contextprinter.py
context_printer-1.3.0.dist-info/METADATA
context_printer-1.3.0.dist-info/WHEEL
context_printer-1.3.0.dist-info/top_level.txt
context_printer-1.3.0.dist-info/RECORD
