Metadata-Version: 2.1
Name: context-printer
Version: 1.3.0
Summary: Tool for simple and appealing display of context in which each operation is executer
Home-page: UNKNOWN
Author: Bonvin Etienne, Rey Valérian
Author-email: etienne.bonvin@epfl.ch, valerian.rey@epfl.ch
License: UNKNOWN
Platform: UNKNOWN
